termux_dev_setup/__init__.py
termux_dev_setup/cli.py
termux_dev_setup/config.py
termux_dev_setup/errors.py
termux_dev_setup/gcloud.py
termux_dev_setup/interactive.py
termux_dev_setup/otel.py
termux_dev_setup/postgres.py
termux_dev_setup/redis.py
termux_dev_setup/service_status.py
termux_dev_setup/views.py
termux_dev_setup/utils/__init__.py
termux_dev_setup/utils/banner.py
termux_dev_setup/utils/lock.py
termux_dev_setup/utils/network.py
termux_dev_setup/utils/postgres_utils.py
termux_dev_setup/utils/shell.py
termux_dev_setup/utils/status.py
termux_dev_setup/utils/syntax_themes.py
termux_dev_setup-2.0.1.dist-info/METADATA
termux_dev_setup-2.0.1.dist-info/WHEEL
termux_dev_setup-2.0.1.dist-info/entry_points.txt
termux_dev_setup-2.0.1.dist-info/top_level.txt
termux_dev_setup-2.0.1.dist-info/RECORD
