Metadata-Version: 2.4
Name: termux-dev-setup
Version: 2.0.1
Summary: Termux development environment setup tool (PostgreSQL, Redis, etc.)
Author-email: dhruv13x <dhruv13x@gmail.com>
License: MIT
Classifier: Programming Language :: Python :: 3
Classifier: Environment :: Console
Requires-Python: >=3.8
Requires-Dist: rich>=13.0.0
Requires-Dist: pygments>=2.15.0
